MANIFEST.in
README.md
setup.cfg
setup.py
rcos_match/__init__.py
rcos_match/apps.py
rcos_match/urls.py
rcos_match/views.py
rcos_match.egg-info/PKG-INFO
rcos_match.egg-info/SOURCES.txt
rcos_match.egg-info/dependency_links.txt
rcos_match.egg-info/requires.txt
rcos_match.egg-info/top_level.txt
rcos_match/static/rcos_match/styles.css
rcos_match/templates/rcos_match/matching/index.html
rcos_match/templates/rcos_match/table/seek_table.html